Metadata-Version: 2.1
Name: quake3rcon
Version: 1.0.0
Summary: A tiny library for using Quake 3's RCON protocol feature for some game servers like FiveM.
Home-page: https://github.com/hellyet/quake3rcon
Author: hellyet
Author-email: leonid.tosterovski@gmail.com
License: MIT
License-File: LICENSE
